sync/__init__.py
sync/sync.py
yacs_adapter-0.1.dist-info/LICENSE
yacs_adapter-0.1.dist-info/METADATA
yacs_adapter-0.1.dist-info/WHEEL
yacs_adapter-0.1.dist-info/entry_points.txt
yacs_adapter-0.1.dist-info/top_level.txt
yacs_adapter-0.1.dist-info/RECORD
